am2940/design.sv
// Code your design here


//registre pe 8 biti pe care le folosesc si pentru registrul
//de adresa si pentru cel de cuvinte
module reg8(di,dout,clk,pl);
  input [7:0] di;
  input clk,pl;
  output reg [7:0] dout;
  always @(posedge clk)
    if(pl==1)
      dout<=di;
endmodule


//registrul de control

module ctrl_reg(di,dout,clk,plcr);
  input [2:0] di;
  input clk,plcr;
  output reg [2:0] dout;
  
  always @(posedge clk)
    if(plcr==1)
      dout<=di;
  
endmodule


//multiplexor 1_2 folosit pentru ambele multiplexoare
module mux(di0,di1,dout,sel);
  
  input [7:0] di0,di1;
  input sel;
  output reg [7:0] dout;
  
  always @(di0 or di1 or sel)
    case(sel)
      1'b0:dout=di0;
      1'b1:dout=di1;
    endcase
  
endmodule


//multiplexor 1_3
module data_mux(di0,di1,di2,dout,seld);
  
  input [7:0] di0,di1;
  input [2:0] di2;
  input [1:0] seld;
  output reg [7:0] dout;
  
  always @(di0 or di1 or di2 or seld)
    begin
    casex(seld)
      2'b00:dout<=di0;
      2'b01:dout<=di1;
      2'b1x:dout<={5'b11111,di2};
      
    endcase
    end
  
endmodule

//numarator-la numaratorul de adresa punem resetul pe 0

module cnt(clk,reset,pl,enable,inc,dec,CIn,COn,in,out);
  input clk,reset,pl,enable,inc,dec,CIn;
  input [7:0] in;
  output reg [7:0] out;
  output COn;
  
  reg [7:0] do_next;
  wire co_inc,co_dec;
  
  always @(posedge clk)
    if(reset==1)
      out<=8'b0;
    else
      out<=do_next;
  always @(pl or enable or inc or dec or in or out or CIn)
    casex({pl,enable,inc,dec,CIn})
      5'b1xxxx:do_next=in;
      5'b0xxx1,5'b00xxx,5'b01000:do_next=out;
      5'b011x0:do_next=out+1;
      5'b01010:do_next=out-1;
      default: do_next=out;
    endcase
  
  assign co_inc=(out===8'hff) & enable &inc & (~CIn);
  assign co_dec=(out===8'b0) & enable & dec & (~CIn);
  assign COn=~(co_inc | co_dec);
endmodule
    


module done_gen(dowc,dowr,doac,cinw,mode,done);
  
  input [7:0] dowc,dowr,doac;
  input [1:0] mode;
  input cinw;
  output reg done;
  
  always @(dowc or dowr or doac or cinw or mode)
    begin
		casex ({ mode, cinw})
        3'b00_0: done=(dowc===8'b1);
		3'b00_1: done=~(|dowc);
		3'b01_0: done=(dowc+1===dowr);
		3'b01_1:done=(dowc===dowr);
		3'b10_x: done=(dowc===doac);
		3'b11_x:done=1'b0;
	endcase
    end
endmodule


module instruction_decoder(i,cr,plar,plwr,sela,selw,plcr,seld,plac,ena,inca,deca,resw,plwc,enw,incw,decw,oedata);
  
  input [2:0] i,cr;
  output reg plar,plwr,sela,selw,plcr,plac,ena,inca,deca,resw,plwc,enw,incw,decw,oedata;
  output reg [1:0] seld;
  
  
  always @(i or cr)
    casex({i,cr})
      6'b000_xxx:{plar,plwr,sela,selw,plcr,seld,plac,ena,inca,deca,resw,plwc,enw,incw,decw,oedata}=17'b00001000000000000; //0-incarcarea registrului de control
      6'b001_xxx:{plar,plwr,sela,selw,plcr,seld,plac,ena,inca,deca,resw,plwc,enw,incw,decw,oedata}=17'b00000100000000001; //1-citim registrul de control
      6'b010_xxx:{plar,plwr,sela,selw,plcr,seld,plac,ena,inca,deca,resw,plwc,enw,incw,decw,oedata}=17'b00000010000000001; //2-citim registrul de cuvinte
      6'b011_xxx:{plar,plwr,sela,selw,plcr,seld,plac,ena,inca,deca,resw,plwc,enw,incw,decw,oedata}=17'b00000000000000001; //3-citim registrul de adrese
      6'b100_xx0,6'b100_x11:{plar,plwr,sela,selw,plcr,seld,plac,ena,inca,deca,resw,plwc,enw,incw,decw,oedata}=17'b00110001000010000; //4-reinitializarea numaratoarelor
      6'b100_001:{plar,plwr,sela,selw,plcr,seld,plac,ena,inca,deca,resw,plwc,enw,incw,decw,oedata}=17'b00100001000100000;
      6'b101_xxx:{plar,plwr,sela,selw,plcr,seld,plac,ena,inca,deca,resw,plwc,enw,incw,decw,oedata}=17'b10000001000000000; //5-datain se incarca in registrul de adrese
      6'b110_xx0,6'b110_x11:{plar,plwr,sela,selw,plcr,seld,plac,ena,inca,deca,resw,plwc,enw,incw,decw,oedata}=17'b01000000000010000; //6-datain se incarca in registrul de cuvinte
      6'b110_x01:{plar,plwr,sela,selw,plcr,seld,plac,ena,inca,deca,resw,plwc,enw,incw,decw,oedata}=17'b01000000000100000;
      6'b111_000:{plar,plwr,sela,selw,plcr,seld,plac,ena,inca,deca,resw,plwc,enw,incw,decw,oedata}=17'b00000000110001010; //7->0 se inc num de adrese si se dec num de cuvinte
      6'b111_0x1:{plar,plwr,sela,selw,plcr,seld,plac,ena,inca,deca,resw,plwc,enw,incw,decw,oedata}=17'b00000000110001100; //7->1,3 se inc num de adrese,se inc num de cuvinte
      6'b111_010:{plar,plwr,sela,selw,plcr,seld,plac,ena,inca,deca,resw,plwc,enw,incw,decw,oedata}=17'b00000000110000000; //7->2 se inc num de adrese,iar num de cuvinte->hold
      6'b111_100:{plar,plwr,sela,selw,plcr,seld,plac,ena,inca,deca,resw,plwc,enw,incw,decw,oedata}=17'b00000000101001010; //7->... asemanatoare doar ca num de adrese de dec
      6'b111_1x1:{plar,plwr,sela,selw,plcr,seld,plac,ena,inca,deca,resw,plwc,enw,incw,decw,oedata}=17'b00000000101001100;
      6'b111_110:{plar,plwr,sela,selw,plcr,seld,plac,ena,inca,deca,resw,plwc,enw,incw,decw,oedata}=17'b00000000101000000;
    endcase
endmodule
      


module am2940(clk,instr,address,datain,dataout,oedata,cina,cona,cinw,conw,done);
  
  //semnalele generale de input si output
  input clk;
  input [2:0] instr;
  output [7:0] address;
  input [7:0] datain;
  output [7:0] dataout;
  output oedata;
  input cina,cinw;
  output cona,conw;
  output done;
  
  
  //semnalele din interior
  
  wire [7:0] doar; //semnalul ce iese din registrul de adrese
  wire [7:0] dowr; //semnalul din registrul de cuvinte
  wire [2:0] docr; //semnalul din registrul de control
  
  wire [7:0] diac; //semnalul ce iese din mux si intra in addr counter
  wire [7:0] diwc; //semnalul ce iese din mux si intra in word counter
  wire [1:0] seld;
  wire [7:0] dowc;
  
  //semnalele ce tin de blocuri
  
  wire plar;
  wire plwr;
  wire sela;
  wire selw;
  wire plcr;
  wire plac;
  wire ena;
  wire inca;
  wire deca;
  wire resw;
  wire plwc;
  wire enw;
  wire incw;
  wire decw;
  
  //instantiem blocurile
  
  reg8 addr_reg(.di(datain),.dout(doar),.clk(clk),.pl(plar));
  
  reg8 word_reg(.di(datain),.dout(dowr),.clk(clk),.pl(plwr));
  
  ctrl_reg ctrl(.di(datain[2:0]),.dout(docr),.clk(clk),.plcr(plcr));
  
  mux addr_mux(.di0(datain),.di1(doar),.dout(diac),.sel(sela));
  
  mux w_mux(.di0(datain),.di1(dowr),.dout(diwc),.sel(selw));
  
  data_mux data(.di0(address),.di1(dowc),.di2(docr),.dout(dataout),.seld(seld));
  
  cnt addr_cnt(.clk(clk),.reset(1'b0),.pl(plac),.enable(ena),.inc(inca),.dec(deca),.CIn(cina),.COn(cona),.in(diac),.out(address));
  
  cnt w_cnt(.clk(clk),.reset(resw),.pl(plwc),.enable(enw),.inc(incw),.dec(decw),.CIn(cinw),.COn(conw),.in(diwc),.out(dowc));
  
  done_gen done_gen_inst(.dowc(dowc),.dowr(dowr),.doac(address),.cinw(cinw),.mode(docr[1:0]),.done(done));
  
  instruction_decoder dec_inst(.i(instr),.cr(docr),.plar(plar),.plwr(plwr),.sela(sela),.selw(selw),.plcr(plcr),.seld(seld),.plac(plac),.ena(ena),.inca(inca),.deca(deca),.resw(resw),.plwc(plwc),.enw(enw),.incw(incw),.decw(decw),.oedata(oedata));
  
endmodule

am2940/testbench.sv
// Code your testbench here
// or browse Examples

module test_am2940;
  
  reg clkt;
  reg [2:0] instrt;
  reg [7:0] dataint;
  reg cinat,cinwt;
  wire [7:0] addresst;
  wire [7:0] dataoutt;
  wire oedatat;
  wire donet;
  wire conat,conwt;
  
  
  am2940 am2940_inst(.clk(clkt),.instr(instrt),.address(addresst),.datain(dataint),.dataout(dataoutt),.oedata(oedatat),.cina(cinat),.cona(conat),.cinw(cinwt),.conw(conwt),.done(donet));
  
  initial
    begin
      #0 clkt=1'b0;
      forever #5 clkt=~clkt;
    end
  
  //facem un task pentru a da mai usor valori
  
  task stimuli_am2940;
    input [2:0] instr;
    input cina,cinw;
    begin
      instrt=instr;
      cinat=cina;
      cinwt=cinw;
    end
  endtask
  
  //ordinea din task 
  //1-instr,2-cina,3-cinw
  
  initial 
    begin
      
      //luam fiecare valoare din cr si trecem prin fiecare instructiune
      
      //-------------------------------------------
      //1. cr=000 ==> AC INCREMENTEAZA, WC DECREMENTEAZA
      
      
      //se scrie in registrul de control
      #0 stimuli_am2940(3'b000,1'b1,1'b1);dataint=8'h0;
      
      //se citeste din registrul de control
      #20 stimuli_am2940(3'b001,1'b1,1'b1);
      
      //se scrie in numaratorul/registrul de adresa 
      #20 dataint=8'b1111_1101; stimuli_am2940(3'b101,1'b1,1'b1);
      
      //se verifica valoarea din numaratorul de adrese
      #20 stimuli_am2940(3'b011,1'b1,1'b1);
      
      //se scrie in numaratorul/registrul de cuvinte
      #20 dataint=8'b0000_0011; stimuli_am2940(3'b110,1'b1,1'b1);
      
      //se verifica valoarea din numaratorul de cuvinte
      #20 stimuli_am2940(3'b010,1'b1,1'b1);
      
      //se incepe numaratoarea in ambele numaratoare si se poate observa ca la AC o sa se activeze CONA
      #20 stimuli_am2940(3'b111,1'b0,1'b0);
      
      //se stopeaza numaratoarea si se reseteaza valoarea cu cea din registre
      #60 stimuli_am2940(3'b100,1'b1,1'b1);
      
      //se verifica valoarea din numaratorul de adrese
      #20 stimuli_am2940(3'b011,1'b1,1'b1);
      
      //se verifica valoarea din numaratorul de cuvinte
      #20 stimuli_am2940(3'b010,1'b1,1'b1);
      
      
      
      //--------------------------------------------
      //2. cr=001 ==> AC INCREMENTEAZA, WC INCREMENTEAZA
      
      
      //se scrie in registrul de control
      #20 stimuli_am2940(3'b000,1'b1,1'b1);dataint=8'h1;
      
      //se citeste din registrul de control
      #20 stimuli_am2940(3'b001,1'b1,1'b1);
      
      //se scrie in numaratorul/registrul de adresa 
      #20 dataint=8'b1000_1010; stimuli_am2940(3'b101,1'b1,1'b1);
      
      //se verifica valoarea din numaratorul de adrese
      #20 stimuli_am2940(3'b011,1'b1,1'b1);
      
      //se scrie in numaratorul/registrul de cuvinte ==>se reseteaza la 0 valoarea de intrare
      #20 dataint=8'b0110_0001; stimuli_am2940(3'b110,1'b1,1'b1);
      
      //se verifica valoarea din numaratorul de cuvinte
      #20 stimuli_am2940(3'b010,1'b1,1'b1);
      
      //se incepe numaratoarea in ambele numaratoare
      #20 stimuli_am2940(3'b111,1'b0,1'b0);
      
      //se stopeaza numaratoarea si se reseteaza valoarea cu cea din registre si la WC o sa se reseteze valoarea la 0
      #60 stimuli_am2940(3'b100,1'b1,1'b1);
      
      //se verifica valoarea din numaratorul de adrese
      #20 stimuli_am2940(3'b011,1'b1,1'b1);
      
      //se verifica valoarea din numaratorul de cuvinte
      #20 stimuli_am2940(3'b010,1'b1,1'b1);
      
      
      //---------------------------------------------
      //3. cr=010 ==> AC INCREMENTEAZA, WC HOLD
      
      //se scrie in registrul de control
      #20 stimuli_am2940(3'b000,1'b1,1'b1);dataint=8'h2;
      
      //se citeste din registrul de control
      #20 stimuli_am2940(3'b001,1'b1,1'b1);
      
      //se scrie in numaratorul/registrul de adresa 
      #20 dataint=8'b1000_1010; stimuli_am2940(3'b101,1'b1,1'b1);
      
      //se verifica valoarea din numaratorul de adrese
      #20 stimuli_am2940(3'b011,1'b1,1'b1);
      
      //se scrie in numaratorul/registrul de cuvinte
      #20 dataint=8'b0110_0001; stimuli_am2940(3'b110,1'b1,1'b1);
      
      //se verifica valoarea din numaratorul de cuvinte
      #20 stimuli_am2940(3'b010,1'b1,1'b1);
      
      //se incepe numaratoarea in ambele numaratoare
      #20 stimuli_am2940(3'b111,1'b0,1'b0);
      
      //se stopeaza numaratoarea si se reseteaza valoarea cu cea din registre
      #60 stimuli_am2940(3'b100,1'b1,1'b1);
      
      //se verifica valoarea din numaratorul de adrese
      #20 stimuli_am2940(3'b011,1'b1,1'b1);
      
      //se verifica valoarea din numaratorul de cuvinte
      #20 stimuli_am2940(3'b010,1'b1,1'b1);
      
      
      //---------------------------------------------
      //4. cr=011 ==> AC INCREMENTEAZA, WC INCREMENTEAZA
      
      //se scrie in registrul de control
      #20 stimuli_am2940(3'b000,1'b1,1'b1);dataint=8'h3;
      
      //se citeste din registrul de control
      #20 stimuli_am2940(3'b001,1'b1,1'b1);
      
      //se scrie in numaratorul/registrul de adresa 
      #20 dataint=8'b1000_1010; stimuli_am2940(3'b101,1'b1,1'b1);
      
      //se verifica valoarea din numaratorul de adrese
      #20 stimuli_am2940(3'b011,1'b1,1'b1);
      
      //se scrie in numaratorul/registrul de cuvinte
      #20 dataint=8'b1111_1101; stimuli_am2940(3'b110,1'b1,1'b1);
      
      //se verifica valoarea din numaratorul de cuvinte
      #20 stimuli_am2940(3'b010,1'b1,1'b1);
      
      //se incepe numaratoarea in ambele numaratoare si la 	WC se va activa CONW
      #20 stimuli_am2940(3'b111,1'b0,1'b0);
      
      //se stopeaza numaratoarea si se reseteaza valoarea cu cea din registre
      #60 stimuli_am2940(3'b100,1'b1,1'b1);
      
      //se verifica valoarea din numaratorul de adrese
      #20 stimuli_am2940(3'b011,1'b1,1'b1);
      
      //se verifica valoarea din numaratorul de cuvinte
      #20 stimuli_am2940(3'b010,1'b1,1'b1);
      
      
      //---------------------------------------------
      //5. cr=100 ==> AC DECREMENTEAZA, WC DECREMENTEAZA
      
      //se scrie in registrul de control
      #20 stimuli_am2940(3'b000,1'b1,1'b1);dataint=8'h4;
      
      //se citeste din registrul de control
      #20 stimuli_am2940(3'b001,1'b1,1'b1);
      
      //se scrie in numaratorul/registrul de adresa 
      #20 dataint=8'b1000_1010; stimuli_am2940(3'b101,1'b1,1'b1);
      
      //se verifica valoarea din numaratorul de adrese
      #20 stimuli_am2940(3'b011,1'b1,1'b1);
      
      //se scrie in numaratorul/registrul de cuvinte
      #20 dataint=8'b0110_0001; stimuli_am2940(3'b110,1'b1,1'b1);
      
      //se verifica valoarea din numaratorul de cuvinte
      #20 stimuli_am2940(3'b010,1'b1,1'b1);
      
      //se incepe numaratoarea in ambele numaratoare
      #20 stimuli_am2940(3'b111,1'b0,1'b0);
      
      //se stopeaza numaratoarea si se reseteaza valoarea cu cea din registre
      #60 stimuli_am2940(3'b100,1'b1,1'b1);
      
      //se verifica valoarea din numaratorul de adrese
      #20 stimuli_am2940(3'b011,1'b1,1'b1);
      
      //se verifica valoarea din numaratorul de cuvinte
      #20 stimuli_am2940(3'b010,1'b1,1'b1);
      
      
      //---------------------------------------------
      //6. cr=101 ==> AC DECREMENTEAZA, WC INCREMENTEAZA
      
      //se scrie in registrul de control
      #20 stimuli_am2940(3'b000,1'b1,1'b1);dataint=8'h5;
      
      //se citeste din registrul de control
      #20 stimuli_am2940(3'b001,1'b1,1'b1);
      
      //se scrie in numaratorul/registrul de adresa 
      #20 dataint=8'b1000_1010; stimuli_am2940(3'b101,1'b1,1'b1);
      
      //se verifica valoarea din numaratorul de adrese
      #20 stimuli_am2940(3'b011,1'b1,1'b1);
      
      //se scrie in numaratorul/registrul de cuvinte ==>se reseteaza la 0 valoarea din numarator
      #20 dataint=8'b0110_0001; stimuli_am2940(3'b110,1'b1,1'b1);
      
      //se verifica valoarea din numaratorul de cuvinte
      #20 stimuli_am2940(3'b010,1'b1,1'b1);
      
      //se incepe numaratoarea in ambele numaratoare
      #20 stimuli_am2940(3'b111,1'b0,1'b0);
      
      //se stopeaza numaratoarea si se reseteaza valoarea cu cea din registre si la WC se va reseta(0)
      #60 stimuli_am2940(3'b100,1'b1,1'b1);
      
      //se verifica valoarea din numaratorul de adrese
      #20 stimuli_am2940(3'b011,1'b1,1'b1);
      
      //se verifica valoarea din numaratorul de cuvinte
      #20 stimuli_am2940(3'b010,1'b1,1'b1);
      
      
      //---------------------------------------------
      //7. cr=110 ==> AC DECREMENTEAZA, WC HOLD
      
      //se scrie in registrul de control
      #20 stimuli_am2940(3'b000,1'b1,1'b1);dataint=8'h6;
      
      //se citeste din registrul de control
      #20 stimuli_am2940(3'b001,1'b1,1'b1);
      
      //se scrie in numaratorul/registrul de adresa 
      #20 dataint=8'b1000_1010; stimuli_am2940(3'b101,1'b1,1'b1);
      
      //se verifica valoarea din numaratorul de adrese
      #20 stimuli_am2940(3'b011,1'b1,1'b1);
      
      //se scrie in numaratorul/registrul de cuvinte
      #20 dataint=8'b0110_0001; stimuli_am2940(3'b110,1'b1,1'b1);
      
      //se verifica valoarea din numaratorul de cuvinte
      #20 stimuli_am2940(3'b010,1'b1,1'b1);
      
      //se incepe numaratoarea in ambele numaratoare,se observa ca WC face hold
      #20 stimuli_am2940(3'b111,1'b0,1'b0);
      
      //se stopeaza numaratoarea si se reseteaza valoarea cu cea din registre
      #60 stimuli_am2940(3'b100,1'b1,1'b1);
      
      //se verifica valoarea din numaratorul de adrese
      #20 stimuli_am2940(3'b011,1'b1,1'b1);
      
      //se verifica valoarea din numaratorul de cuvinte
      #20 stimuli_am2940(3'b010,1'b1,1'b1);
      
      
      //---------------------------------------------
      //8. cr=111 ==> AC DECREMENTEAZA, WC INCREMENTEAZA
      
      //se scrie in registrul de control
      #20 stimuli_am2940(3'b000,1'b1,1'b1);dataint=8'h7;
      
      //se citeste din registrul de control
      #20 stimuli_am2940(3'b001,1'b1,1'b1);
      
      //se scrie in numaratorul/registrul de adresa 
      #20 dataint=8'b1000_1010; stimuli_am2940(3'b101,1'b1,1'b1);
      
      //se verifica valoarea din numaratorul de adrese
      #20 stimuli_am2940(3'b011,1'b1,1'b1);
      
      //se scrie in numaratorul/registrul de cuvinte
      #20 dataint=8'b0110_0001; stimuli_am2940(3'b110,1'b1,1'b1);
      
      //se verifica valoarea din numaratorul de cuvinte
      #20 stimuli_am2940(3'b010,1'b1,1'b1);
      
      //se incepe numaratoarea in ambele numaratoare
      #20 stimuli_am2940(3'b111,1'b0,1'b0);
      
      //se stopeaza numaratoarea si se reseteaza valoarea cu cea din registre
      #60 stimuli_am2940(3'b100,1'b1,1'b1);
      
      //se verifica valoarea din numaratorul de adrese
      #20 stimuli_am2940(3'b011,1'b1,1'b1);
      
      //se verifica valoarea din numaratorul de cuvinte
      #20 stimuli_am2940(3'b010,1'b1,1'b1);
      
      //-----------------------------------------
      
    end
   initial
    begin
      #2500 $finish;
    end
  
  initial
    begin
      $dumpfile("dump.vcd");
      $dumpvars(0,am2940_inst);
    end
endmodule

am2940/dump.vcd
$date
	Tue Apr  4 19:12:31 2023
$end
$version
	Icarus Verilog
$end
$timescale
	1s
$end
$scope module test_am2940 $end
$scope module am2940_inst $end
$var wire 8 ! address [7:0] $end
$var wire 1 " cina $end
$var wire 1 # cinw $end
$var wire 1 $ clk $end
$var wire 1 % cona $end
$var wire 1 & conw $end
$var wire 8 ' datain [7:0] $end
$var wire 8 ( dataout [7:0] $end
$var wire 1 ) deca $end
$var wire 1 * decw $end
$var wire 8 + diac [7:0] $end
$var wire 8 , diwc [7:0] $end
$var wire 8 - doar [7:0] $end
$var wire 3 . docr [2:0] $end
$var wire 1 / done $end
$var wire 8 0 dowc [7:0] $end
$var wire 8 1 dowr [7:0] $end
$var wire 1 2 ena $end
$var wire 1 3 enw $end
$var wire 1 4 inca $end
$var wire 1 5 incw $end
$var wire 3 6 instr [2:0] $end
$var wire 1 7 oedata $end
$var wire 1 8 plac $end
$var wire 1 9 plar $end
$var wire 1 : plcr $end
$var wire 1 ; plwc $end
$var wire 1 < plwr $end
$var wire 1 = resw $end
$var wire 1 > sela $end
$var wire 2 ? seld [1:0] $end
$var wire 1 @ selw $end
$scope module addr_reg $end
$var wire 1 $ clk $end
$var wire 8 A di [7:0] $end
$var wire 1 9 pl $end
$var reg 8 B dout [7:0] $end
$upscope $end
$scope module word_reg $end
$var wire 1 $ clk $end
$var wire 8 C di [7:0] $end
$var wire 1 < pl $end
$var reg 8 D dout [7:0] $end
$upscope $end
$scope module ctrl $end
$var wire 1 $ clk $end
$var wire 3 E di [2:0] $end
$var wire 1 : plcr $end
$var reg 3 F dout [2:0] $end
$upscope $end
$scope module addr_mux $end
$var wire 8 G di0 [7:0] $end
$var wire 8 H di1 [7:0] $end
$var wire 1 > sel $end
$var reg 8 I dout [7:0] $end
$upscope $end
$scope module w_mux $end
$var wire 8 J di0 [7:0] $end
$var wire 8 K di1 [7:0] $end
$var wire 1 @ sel $end
$var reg 8 L dout [7:0] $end
$upscope $end
$scope module data $end
$var wire 8 M di0 [7:0] $end
$var wire 8 N di1 [7:0] $end
$var wire 3 O di2 [2:0] $end
$var wire 2 P seld [1:0] $end
$var reg 8 Q dout [7:0] $end
$upscope $end
$scope module addr_cnt $end
$var wire 1 " CIn $end
$var wire 1 % COn $end
$var wire 1 $ clk $end
$var wire 1 R co_dec $end
$var wire 1 S co_inc $end
$var wire 1 ) dec $end
$var wire 1 2 enable $end
$var wire 8 T in [7:0] $end
$var wire 1 4 inc $end
$var wire 1 8 pl $end
$var wire 1 U reset $end
$var reg 8 V do_next [7:0] $end
$var reg 8 W out [7:0] $end
$upscope $end
$scope module w_cnt $end
$var wire 1 # CIn $end
$var wire 1 & COn $end
$var wire 1 $ clk $end
$var wire 1 X co_dec $end
$var wire 1 Y co_inc $end
$var wire 1 * dec $end
$var wire 1 3 enable $end
$var wire 8 Z in [7:0] $end
$var wire 1 5 inc $end
$var wire 1 ; pl $end
$var wire 1 = reset $end
$var reg 8 [ do_next [7:0] $end
$var reg 8 \ out [7:0] $end
$upscope $end
$scope module done_gen_inst $end
$var wire 1 # cinw $end
$var wire 8 ] doac [7:0] $end
$var wire 8 ^ dowc [7:0] $end
$var wire 8 _ dowr [7:0] $end
$var wire 2 ` mode [1:0] $end
$var reg 1 a done $end
$upscope $end
$scope module dec_inst $end
$var wire 3 b cr [2:0] $end
$var wire 3 c i [2:0] $end
$var reg 1 d deca $end
$var reg 1 e decw $end
$var reg 1 f ena $end
$var reg 1 g enw $end
$var reg 1 h inca $end
$var reg 1 i incw $end
$var reg 1 j oedata $end
$var reg 1 k plac $end
$var reg 1 l plar $end
$var reg 1 m plcr $end
$var reg 1 n plwc $end
$var reg 1 o plwr $end
$var reg 1 p resw $end
$var reg 1 q sela $end
$var reg 2 r seld [1:0] $end
$var reg 1 s selw $end
$upscope $end
$upscope $end
$upscope $end
$enddefinitions $end
#0
$dumpvars
0s
b0 r
0q
0p
0o
0n
1m
0l
0k
0j
0i
0h
0g
0f
0e
0d
b0 c
bx b
xa
bx `
bx _
bx ^
bx ]
bx \
bx [
b0 Z
0Y
0X
bx W
bx V
0U
b0 T
0S
0R
bx Q
b0 P
bx O
bx N
bx M
b0 L
bx K
b0 J
b0 I
bx H
b0 G
bx F
b0 E
bx D
b0 C
bx B
b0 A
0@
b0 ?
0>
0=
0<
0;
1:
09
08
07
b0 6
05
04
03
02
bx 1
bx 0
x/
bx .
bx -
b0 ,
b0 +
0*
0)
bx (
b0 '
1&
1%
0$
1#
1"
bx !
$end
#5
b0 `
b0 F
b0 .
b0 O
b0 b
1$
#10
0$
#15
1$
#20
b11111000 Q
b11111000 (
0m
0:
b10 r
b10 ?
b10 P
1j
17
0$
b1 6
b1 c
#25
1$
#30
0$
#35
1$
#40
bx Q
bx (
b11111101 V
1l
19
b0 r
b0 ?
b0 P
1k
18
0j
07
b11111101 L
b11111101 ,
b11111101 Z
b11111101 I
b11111101 +
b11111101 T
b101 E
0$
b101 6
b101 c
b11111101 '
b11111101 A
b11111101 C
b11111101 G
b11111101 J
#45
b11111101 Q
b11111101 (
b11111101 B
b11111101 -
b11111101 H
b11111101 W
b11111101 !
b11111101 M
b11111101 ]
1$
#50
0$
#55
1$
#60
0l
09
0k
08
1j
17
0$
b11 6
b11 c
#65
1$
#70
0$
#75
1$
#80
b11 [
1o
1<
1n
1;
0j
07
b11 L
b11 ,
b11 Z
b11 I
b11 +
b11 T
b11 E
0$
b110 6
b110 c
b11 '
b11 A
b11 C
b11 G
b11 J
#85
0a
0/
b11 D
b11 1
b11 K
b11 _
b11 \
b11 0
b11 N
b11 ^
1$
#90
0$
#95
1$
#100
b11 Q
b11 (
0o
0<
b1 r
b1 ?
b1 P
0n
0;
1j
17
0$
b10 6
b10 c
#105
1$
#110
0$
#115
1$
#120
b11111101 Q
b11111101 (
b10 [
b11111110 V
b0 r
b0 ?
b0 P
1f
12
1h
14
1g
13
1e
1*
0j
07
0$
0#
0"
b111 6
b111 c
#125
b11111110 Q
b11111110 (
b11111111 V
b1 [
b11111110 W
b11111110 !
b11111110 M
b11111110 ]
b10 \
b10 0
b10 N
b10 ^
1$
#130
0$
#135
b11111111 Q
b11111111 (
0%
1S
b0 [
1a
1/
b0 V
b1 \
b1 0
b1 N
b1 ^
b11111111 W
b11111111 !
b11111111 M
b11111111 ]
1$
#140
0$
#145
b0 Q
b0 (
1%
0&
0S
1X
b1 V
0a
0/
b11111111 [
b0 W
b0 !
b0 M
b0 ]
b0 \
b0 0
b0 N
b0 ^
1$
#150
0$
#155
b1 Q
b1 (
1&
0X
b11111110 [
b10 V
b11111111 \
b11111111 0
b11111111 N
b11111111 ^
b1 W
b1 !
b1 M
b1 ]
1$
#160
0$
#165
b10 Q
b10 (
b11 V
b11111101 [
b10 W
b10 !
b10 M
b10 ]
b11111110 \
b11111110 0
b11111110 N
b11111110 ^
1$
#170
0$
#175
b11 Q
b11 (
b11111100 [
b100 V
b11111101 \
b11111101 0
b11111101 N
b11111101 ^
b11 W
b11 !
b11 M
b11 ]
1$
#180
b11111101 I
b11111101 +
b11111101 T
b11 [
b11111101 V
1q
1>
1s
1@
1k
18
0f
02
0h
04
1n
1;
0g
03
0e
0*
0$
1#
1"
b100 6
b100 c
#185
b11111101 Q
b11111101 (
b11111101 W
b11111101 !
b11111101 M
b11111101 ]
b11 \
b11 0
b11 N
b11 ^
1$
#190
0$
#195
1$
#200
b11 I
b11 +
b11 T
0q
0>
0s
0@
0k
08
0n
0;
1j
17
0$
b11 6
b11 c
#205
1$
#210
0$
#215
1$
#220
b11 Q
b11 (
b1 r
b1 ?
b1 P
0$
b10 6
b10 c
#225
1$
#230
0$
#235
1$
#240
b11111101 Q
b11111101 (
b1 L
b1 ,
b1 Z
b1 I
b1 +
b1 T
b1 E
1m
1:
b0 r
b0 ?
b0 P
0j
07
0$
b1 '
b1 A
b1 C
b1 G
b1 J
b0 6
b0 c
#245
1a
1/
b1 `
b1 F
b1 .
b1 O
b1 b
1$
#250
0$
#255
1$
#260
b11111001 Q
b11111001 (
0m
0:
b10 r
b10 ?
b10 P
1j
17
0$
b1 6
b1 c
#265
1$
#270
0$
#275
1$
#280
b11111101 Q
b11111101 (
b10001010 V
1l
19
b0 r
b0 ?
b0 P
1k
18
0j
07
b10001010 L
b10001010 ,
b10001010 Z
b10001010 I
b10001010 +
b10001010 T
b10 E
0$
b101 6
b101 c
b10001010 '
b10001010 A
b10001010 C
b10001010 G
b10001010 J
#285
b10001010 Q
b10001010 (
b10001010 B
b10001010 -
b10001010 H
b10001010 W
b10001010 !
b10001010 M
b10001010 ]
1$
#290
0$
#295
1$
#300
0l
09
0k
08
1j
17
0$
b11 6
b11 c
#305
1$
#310
0$
#315
1$
#320
1o
1<
1p
1=
0j
07
b1100001 L
b1100001 ,
b1100001 Z
b1100001 I
b1100001 +
b1100001 T
b1 E
0$
b110 6
b110 c
b1100001 '
b1100001 A
b1100001 C
b1100001 G
b1100001 J
#325
0a
0/
b0 [
b1100001 D
b1100001 1
b1100001 K
b1100001 _
b0 \
b0 0
b0 N
b0 ^
1$
#330
0$
#335
1$
#340
b0 Q
b0 (
0o
0<
b1 r
b1 ?
b1 P
0p
0=
1j
17
0$
b10 6
b10 c
#345
1$
#350
0$
#355
1$
#360
b10001010 Q
b10001010 (
b1 [
b10001011 V
b0 r
b0 ?
b0 P
1f
12
1h
14
1g
13
1i
15
0j
07
0$
0#
0"
b111 6
b111 c
#365
b10001011 Q
b10001011 (
b10001100 V
b10 [
b10001011 W
b10001011 !
b10001011 M
b10001011 ]
b1 \
b1 0
b1 N
b1 ^
1$
#370
0$
#375
b10001100 Q
b10001100 (
b11 [
b10001101 V
b10 \
b10 0
b10 N
b10 ^
b10001100 W
b10001100 !
b10001100 M
b10001100 ]
1$
#380
0$
#385
b10001101 Q
b10001101 (
b10001110 V
b100 [
b10001101 W
b10001101 !
b10001101 M
b10001101 ]
b11 \
b11 0
b11 N
b11 ^
1$
#390
0$
#395
b10001110 Q
b10001110 (
b101 [
b10001111 V
b100 \
b100 0
b100 N
b100 ^
b10001110 W
b10001110 !
b10001110 M
b10001110 ]
1$
#400
0$
#405
b10001111 Q
b10001111 (
b10010000 V
b110 [
b10001111 W
b10001111 !
b10001111 M
b10001111 ]
b101 \
b101 0
b101 N
b101 ^
1$
#410
0$
#415
b10010000 Q
b10010000 (
b111 [
b10010001 V
b110 \
b110 0
b110 N
b110 ^
b10010000 W
b10010000 !
b10010000 M
b10010000 ]
1$
#420
b10001010 I
b10001010 +
b10001010 T
b110 [
b10001010 V
1q
1>
1k
18
0f
02
0h
04
1p
1=
0g
03
0i
05
0$
1#
1"
b100 6
b100 c
#425
b10001010 Q
b10001010 (
b0 [
b10001010 W
b10001010 !
b10001010 M
b10001010 ]
b0 \
b0 0
b0 N
b0 ^
1$
#430
0$
#435
1$
#440
b1100001 I
b1100001 +
b1100001 T
0q
0>
0k
08
0p
0=
1j
17
0$
b11 6
b11 c
#445
1$
#450
0$
#455
1$
